README.md
setup.py
linkedin/__init__.py
linkedin/__main__.py
linkedin/cli.py
linkedin/commands/__init__.py
linkedin/commands/command.py
linkedin/commands/config.py
linkedin/commands/help.py
linkedin/commands/login.py
linkedin/commands/me.py
linkedin/commands/post.py
linkedin/commands/version.py
linkedin/resources/__init__.py
linkedin/resources/version.py
linkedin/utils/__init__.py
linkedin/utils/config.py
linkedin/utils/linkedin.py
linkedin_cli.egg-info/PKG-INFO
linkedin_cli.egg-info/SOURCES.txt
linkedin_cli.egg-info/dependency_links.txt
linkedin_cli.egg-info/entry_points.txt
linkedin_cli.egg-info/top_level.txt