Metadata-Version: 2.1
Name: linkedin-cli
Version: 0.1.0
Summary: linkedin-cli - Linkedin Command Line Interface
Home-page: https://linkedin-cli.tigillo.com
Author: tigillo
Author-email: linkedin-cli@tigillo.com
License: UNKNOWN
Download-URL: https://github.com/tigillo/linkedin-cli/archive/0.1.0.tar.gz
Keywords: linkedin,linkedin-cli,linkedin automation
Platform: UNKNOWN
